flexai/__init__.py
flexai/agent.py
flexai/capabilities/__init__.py
flexai/capabilities/add_context.py
flexai/capabilities/limit_tool_use.py
flexai/capabilities/memory.py
flexai/capabilities/truncate_messages.py
flexai/capability.py
flexai/llm/__init__.py
flexai/llm/anthropic_client.py
flexai/llm/client.py
flexai/message.py
flexai/tool.py
instinct-0.1.0a1.dist-info/METADATA
instinct-0.1.0a1.dist-info/WHEEL
instinct-0.1.0a1.dist-info/RECORD
