Metadata-Version: 2.1
Name: instinct
Version: 0.1.0a1
Summary: A flexible agent framework.
Author: Nikhil Rao
Author-email: nikhil@reflex.dev
Requires-Python: >=3.11,<4.0
Classifier: Programming Language :: Python :: 3
Classifier: Programming Language :: Python :: 3.11
Classifier: Programming Language :: Python :: 3.12
